[
  {
    "id": 0,
    "project_name": "Passport Preparatory Academy",
    "imageUrl": "/assets/images/PPA.png",
    "url": "https://pp-academy-f.onrender.com/home"
  },
  {
    "id": 1,
    "project_name": "AI Enterprise Dashboard",
    "imageUrl": "/assets/images/Ai Enterprise Dashboard.png",
    "url": "https://enterprise-dashboard-frontend-lsjr.onrender.com/dashboard"
  },
  {
    "id": 2,
    "project_name": "Ecommerce Store",
    "imageUrl": "/assets/images/FlexEcomstore.png",
    "url": "https://ecommerce-szco.onrender.com/"
  },
  {
    "id": 3,
    "project_name": "Akira Movie Application",
    "imageUrl": "/assets/images/Akira Movie Site.png",
    "url": "https://akira-movie-app-1.onrender.com/"
  },
  {
    "id": 4,
    "project_name": "Trivia Quiz Application",
    "imageUrl": "/assets/images/Trivia Game.png",
    "url": "https://capstone-trivia.onrender.com/"
  },
  {
    "id": 5,
    "project_name": "Original Portfolio Site",
    "imageUrl": "/assets/images/originalps.png",
    "url": "https://kingdrahggo.github.io/portfolio-site/"
  },
  {
    "id": 6,
    "project_name": "Tic Tac Toe Game",
    "imageUrl": "/assets/images/React Tic Tac Toe.png",
    "url": "https://tictactoereact.onrender.com"
  },
  {
    "id": 7,
    "project_name": "To Do List Application",
    "imageUrl": "/assets/images/To Do List Mean Stack.png",
    "url": "https://to-do-list-mean-f.onrender.com/"
  },
  {
    "id": 8,
    "project_name": "Pig Latin Application",
    "imageUrl": "/assets/images/Pig Latin Generator.png",
    "url": "https://piglatin-generator.onrender.com"
  }
]